vladrabbit_test/__init__.py
vladrabbit_test-0.1.0.dist-info/METADATA
vladrabbit_test-0.1.0.dist-info/WHEEL
vladrabbit_test-0.1.0.dist-info/RECORD
